{
  "name": "中青看点定时任务订阅",
  "desc": "无",
  "date": "2021-11-17",
  "author": "https://t.me/ShaolinTemple1",
  "resource": "https://ghproxy.com/https://raw.githubusercontent.com/knowledgeablelmh/Android-V2P/main/zqkd/zq_cron.json",
  "list": [
    {
      "name": "中青看点签到",
      "type": "cron",
      "time": "30 0,12 * * *",
      "job": {
        "type": "runjs",
        "target": "https://ghproxy.com/https://raw.githubusercontent.com/knowledgeablelmh/Android-V2P/main/zqkd/zqqd.js"
      }
    },
    {
      "name": "中青看点文章",
      "type": "cron",
      "time": "30 7,12,18 * * *",
      "running": true,
      "job": {
        "type": "runjs",
        "target": "https://ghproxy.com/https://raw.githubusercontent.com/knowledgeablelmh/Android-V2P/main/zqkd/zqwz.js"
      }
    },
    {
     "name": "中青看点看看赚",
      "type": "cron",
      "time": "45 9,10 * * *",
      "running": true,
      "job": {
        "type": "runjs",
        "target": "https://ghproxy.com/https://raw.githubusercontent.com/knowledgeablelmh/Android-V2P/main/zqkd/zqkkz.js"
      }
    },
    {
      "name": "中青看点火爆转发",
      "type": "cron",
      "time": "15 6,12,18 * * *",
      "running": true,
      "job": {
        "type": "runjs",
        "target": "https://ghproxy.com/https://raw.githubusercontent.com/knowledgeablelmh/Android-V2P/main/zqkd/zq_share.js"
      }
    },
    {
      "name": "中青看点福利视频",
      "type": "cron",
      "time": "30 12,13 * * *",
      "running": true,
      "job": {
        "type": "runjs",
        "target": "https://ghproxy.com/https://raw.githubusercontent.com/knowledgeablelmh/Android-V2P/main/zqkd/zq_Adv_video.js"
      }
    },
    {
      "name": "中青看点每日任务宝箱领取",
      "type": "cron",
      "time": "30 20,21 * * *",
      "running": true,
      "job": {
        "type": "runjs",
        "target": "https://ghproxy.com/https://raw.githubusercontent.com/knowledgeablelmh/Android-V2P/main/zqkd/zqbox.js"
      }
    },
    {
      "name": "中青看点每日收益统计",
      "type": "cron",
      "time": "15 23 * * *",
      "running": true,
      "job": {
        "type": "runjs",
        "target": "https://ghproxy.com/https://raw.githubusercontent.com/knowledgeablelmh/Android-V2P/main/zqkd/zq_today_score.js"
      }
    },
    {
      "name": "中青看点好友签到红包",
      "type": "cron",
      "time": "15 7,8 * * *",
      "running": true,
      "job": {
        "type": "runjs",
        "target": "https://ghproxy.com/https://raw.githubusercontent.com/knowledgeablelmh/Android-V2P/main/zqkd/zq_friendSign.js"
      }
    },
    {
      "name": "中青看点抽奖",
      "type": "cron",
      "time": "30 8,10 * * *",
      "running": true,
      "job": {
        "type": "runjs",
        "target": "https://ghproxy.com/https://raw.githubusercontent.com/knowledgeablelmh/Android-V2P/main/zqkd/zq_Rotary.js"
      }
    },
    {
      "name": "中青看点打卡赚",
      "type": "cron",
      "time": "45 5,9 * * *",
      "running": true,
      "job": {
        "type": "runjs",
        "target": "https://ghproxy.com/https://raw.githubusercontent.com/knowledgeablelmh/Android-V2P/main/zqkd/zq_wakeup.js"
      }
    },
    {
      "name": "中青看点搜索赚",
      "type": "cron",
      "time": "30 6,7 * * *",
      "running": true,
      "job": {
        "type": "runjs",
        "target": "https://ghproxy.com/https://raw.githubusercontent.com/knowledgeablelmh/Android-V2P/main/zqkd/zqssz.js"
      }
    },
    {
      "name": "中青看点浏览赚",
      "type": "cron",
      "time": "45 6,7 * * *",
      "running": true,
      "job": {
        "type": "runjs",
        "target": "https://ghproxy.com/https://raw.githubusercontent.com/knowledgeablelmh/Android-V2P/main/zqkd/zqllz.js"
      }
    },
    {
      "name": "中青看点阅读翻倍",
      "type": "cron",
      "time": "30 5,6 * * *",
      "running": true,
      "job": {
        "type": "runjs",
        "target": "https://ghproxy.com/https://raw.githubusercontent.com/knowledgeablelmh/Android-V2P/main/zqkd/zq_double.js"
      }
    },
    {
      "name": "中青看点5分钟60分钟任务",
      "type": "cron",
      "time": "0 20,21 * * *",
      "job": {
        "type": "runjs",
        "target": "https://ghproxy.com/https://raw.githubusercontent.com/knowledgeablelmh/Android-V2P/main/zqkd/zq_5_60.js"
      }
    },
    {
      "name": "中青自动提现",
      "type": "cron",
      "time": "30 23 * * *",
      "running": true,
      "job": {
        "type": "runjs",
        "target": "https://ghproxy.com/https://raw.githubusercontent.com/knowledgeablelmh/Android-V2P/main/zqkd/zq_withdraw.js"
      }
    }

  ]
}
